LICENSE.txt
MANIFEST.in
README.md
requirements.txt
setup.cfg
setup.py
helpus/__init__.py
helpus/core.py
helpus/version.py
helpus.egg-info/PKG-INFO
helpus.egg-info/SOURCES.txt
helpus.egg-info/dependency_links.txt
helpus.egg-info/requires.txt
helpus.egg-info/top_level.txt
helpus/resources/__init__.py
helpus/resources/resources.py
helpus/resources/ico/snake.ico
helpus/resources/ico/snake_ico.ico