Metadata-Version: 2.1
Name: helpus
Version: 0.0.1
Summary: Simple Gui to call Pdb in GUI Apps
Home-page: https://github.com/tov101/HelpUs
Author: Ovidiu Mihaila
Author-email: ov.mihaila@gmail.com
License: UNKNOWN
Download-URL: https://github.com/tov101/HelpUs/archive/refs/tags/v0.0.1.tar.gz
Keywords: HelpUs -> BreakPoint In Execution Module
Platform: UNKNOWN
Classifier: Development Status :: 3 - Alpha
Classifier: Intended Audience :: Developers
Classifier: Topic :: Software Development :: Bug Tracking
Classifier: License :: Public Domain
Classifier: Programming Language :: Python :: 3.7
Classifier: Programming Language :: Python :: 3.8
Classifier: Programming Language :: Python :: 3.9
License-File: LICENSE.txt
